wsingular/__init__.py
wsingular/distance.py
wsingular/utils.py
wsingular-0.1.7.dist-info/LICENSE
wsingular-0.1.7.dist-info/METADATA
wsingular-0.1.7.dist-info/WHEEL
wsingular-0.1.7.dist-info/top_level.txt
wsingular-0.1.7.dist-info/RECORD
