Metadata-Version: 2.1
Name: wsingular
Version: 0.1.7
Summary: Wasserstein Singular Vectors
Home-page: https://github.com/gjhuizing/wsingular
Author: Geert-Jan Huizing, Laura Cantini, Gabriel Peyré
Author-email: huizing@ens.fr
License-File: LICENSE
Requires-Dist: torch
Requires-Dist: pandas
Requires-Dist: scikit-learn
Requires-Dist: seaborn
Requires-Dist: matplotlib
Requires-Dist: scipy
Requires-Dist: tqdm
Requires-Dist: numpy
Requires-Dist: pot (>=0.8)
Requires-Dist: networkx
